tnqmetro/__init__.py
tnqmetro-1.1.0.dist-info/LICENSE
tnqmetro-1.1.0.dist-info/METADATA
tnqmetro-1.1.0.dist-info/WHEEL
tnqmetro-1.1.0.dist-info/top_level.txt
tnqmetro-1.1.0.dist-info/RECORD
