Metadata-Version: 2.1
Name: tnqmetro
Version: 1.1.0
Summary: Tensor-network based package for efficient quantum metrology computations.
Home-page: https://github.com/kchabuda/TNQMetro
Author: Krzysztof Chabuda
Author-email: krzysztof.chabuda@fuw.edu.pl
License: UNKNOWN
Project-URL: Documentation, https://github.com/kchabuda/TNQMetro/wiki
Platform: UNKNOWN
Classifier: Programming Language :: Python :: 3
Classifier: License :: OSI Approved :: MIT License
Classifier: Operating System :: OS Independent
Classifier: Topic :: Scientific/Engineering
Classifier: Intended Audience :: Science/Research
Classifier: Development Status :: 5 - Production/Stable
Requires-Python: >=3.6
License-File: LICENSE
Requires-Dist: numpy (>=1.11.0)
Requires-Dist: ncon
